passforge/__init__.py
passforge/passforge.py
passforge-0.4.dist-info/LICENSE
passforge-0.4.dist-info/METADATA
passforge-0.4.dist-info/WHEEL
passforge-0.4.dist-info/entry_points.txt
passforge-0.4.dist-info/top_level.txt
passforge-0.4.dist-info/RECORD
