Metadata-Version: 2.1
Name: passforge
Version: 0.4
Summary: PassForge is an advanced password generation tool designed to provide users with highly customizable and secure password options. It blends sophistication with flexibility, allowing users to craft passwords tailored to their specific needs, enhancing both security and usability in a user-friendly manner.
Home-page: https://github.com/veilwr4ith/PassForge
Author: veilwr4ith
Author-email: hidetheveil@gmail.com
Classifier: Programming Language :: Python :: 3
Classifier: License :: OSI Approved :: MIT License
Classifier: Operating System :: OS Independent
License-File: LICENSE
